AUTHORS
CHANGELOG
LICENSE
MANIFEST.in
README.rst
setup.py
doc/teleforma-all.dot
doc/teleforma-all.pdf
doc/teleforma.dot
doc/teleforma.pdf
example/.directory
example/__init__.py
example/manage.py
example/settings.py
example/urls.py
example/wsgi.py
teleforma/__init__.py
teleforma/admin.py
teleforma/fields.py
teleforma/forms.py
teleforma/middleware.py
teleforma/models.py
teleforma/settings.py
teleforma/tests.py
teleforma/urls.py
teleforma/views.py
teleforma/locale/fr/LC_MESSAGES/django.mo
teleforma/locale/fr/LC_MESSAGES/django.po
teleforma/management/__init__.py
teleforma/management/commands/__init__.py
teleforma/management/commands/teleforma-export-professors.py
teleforma/management/commands/teleforma-export-users.py
teleforma/management/commands/teleforma-import-conferences.py
teleforma/management/commands/teleforma-import-courses-xls.py
teleforma/management/commands/teleforma-import-courses.py
teleforma/management/commands/teleforma-import-professors.py
teleforma/management/commands/teleforma-import-users-pb-debug.py
teleforma/management/commands/teleforma-import-users-pb.py
teleforma/management/commands/teleforma-import-users.py
teleforma/management/commands/teleforma-push-conferences.py
teleforma/management/commands/teleforma-reset-all-passwords-with-mail.py
teleforma/management/commands/teleforma-reset-all-passwords.py
teleforma/migrations/0001_initial.py
teleforma/migrations/0002_auto__add_coursetype__add_field_course_type.py
teleforma/migrations/0003_auto__add_field_course_chat_room.py
teleforma/migrations/0004_auto__add_field_training_category__del_field_course_category.py
teleforma/migrations/0005_auto__add_field_profile_date_added.py
teleforma/migrations/0006_auto.py
teleforma/migrations/0007_auto__del_field_course_chat_room__add_field_professor_training.py
teleforma/migrations/0008_auto__add_field_course_date_modified.py
teleforma/migrations/0009_auto__add_field_media_title__add_field_media_description__add_field_me.py
