Metadata-Version: 1.0
Name: TeleForma
Version: 0.8
Summary: open web multimedia e-learning platform
Home-page: https://github.com/yomguy/teleforma
Author: Guillaume Pellerin
Author-email: yomguy@parisson.com
License: CeCILL v2
Platform: OS Independent
Classifier: Environment :: Web Environment
Classifier: Framework :: Django
Classifier: Intended Audience :: Education
Classifier: Programming Language :: Python
Classifier: Programming Language :: JavaScript
Classifier: Topic :: Internet :: WWW/HTTP :: Dynamic Content
Classifier: Topic :: Internet :: WWW/HTTP :: WSGI :: Application
Classifier: Topic :: Multimedia :: Sound/Audio
Classifier: Topic :: Multimedia :: Sound/Audio :: Analysis
Classifier: Topic :: Multimedia :: Sound/Audio :: Players
Classifier: Topic :: Scientific/Engineering :: Information Analysis
Classifier: Topic :: System :: Archiving
